AUTHORS
CHANGELOG
INSTALL
LICENSE
MANIFEST.in
README.rst
VERSION
setup.py
django_plainpasswordhasher/__init__.py
django_plainpasswordhasher/hashers.py
django_plainpasswordhasher/tests.py
django_plainpasswordhasher.egg-info/PKG-INFO
django_plainpasswordhasher.egg-info/SOURCES.txt
django_plainpasswordhasher.egg-info/dependency_links.txt
django_plainpasswordhasher.egg-info/not-zip-safe
django_plainpasswordhasher.egg-info/requires.txt
django_plainpasswordhasher.egg-info/top_level.txt