Metadata-Version: 1.1
Name: django-plainpasswordhasher
Version: 0.2
Summary: Dummy (plain text) password hashing for Django.
Home-page: https://github.com/novapost/django-plainpasswordhasher
Author: Boris Feld
Author-email: lothiraldan@gmail.com
License: BSD
Platform: UNKNOWN
Classifier: Development Status :: 4 - Beta
Classifier: License :: OSI Approved :: BSD License
Classifier: Programming Language :: Python :: 2.7
Classifier: Framework :: Django
Classifier: Topic :: Security :: Cryptography
Classifier: Topic :: Software Development :: Testing
